{
	"class" : {
		"buttonHeight" : "goldfisch 6/22/2015 05:17",
		"buttonWidth" : "goldfisch 6/22/2015 05:18",
		"defaultButtonPadding" : "goldfisch 6/22/2015 05:41",
		"defaultButtonSize" : "goldfisch 6/22/2015 05:42",
		"defaultGuiPosition" : "goldfisch 6/22/2015 03:31",
		"defaultGuiPreviewBox" : "goldfisch 6/22/2015 05:33",
		"defaultGuiRow0Pos1" : "goldfisch 6/22/2015 05:14",
		"defaultGuiRow0Pos2" : "goldfisch 6/22/2015 05:43",
		"defaultGuiRow1Pos1" : "goldfisch 6/22/2015 05:23",
		"defaultGuiRow1Pos2" : "goldfisch 6/22/2015 05:44",
		"defaultGuiRow2Pos1" : "goldfisch 6/22/2015 05:24",
		"defaultGuiRow2Pos2" : "goldfisch 6/22/2015 05:44",
		"defaultGuiRow3Pos1" : "goldfisch 6/22/2015 05:25",
		"dimension" : "goldfisch 6/22/2015 05:37",
		"label" : "goldfisch 6/22/2015 05:29",
		"open" : "goldfisch 6/21/2015 12:57",
		"stringDeleteCaptureMorph" : "goldfisch 6/21/2015 12:57",
		"stringEnterMode" : "goldfisch 6/21/2015 12:57",
		"stringHidingKeys" : "goldfisch 6/21/2015 12:57",
		"stringLeaveMode" : "goldfisch 6/21/2015 12:57",
		"stringOpenCaptureMorph" : "goldfisch 6/21/2015 12:57",
		"stringShowingKeys" : "goldfisch 6/21/2015 12:57",
		"stringStartRecord" : "goldfisch 6/21/2015 12:57",
		"stringStopRecord" : "goldfisch 6/21/2015 12:57" },
	"instance" : {
		"applyButton" : "goldfisch 6/21/2015 12:57",
		"applyButton:" : "goldfisch 6/21/2015 12:57",
		"applyCurrentFactor" : "goldfisch 6/21/2015 12:57",
		"button" : "goldfisch 6/21/2015 12:57",
		"button:" : "goldfisch 6/21/2015 12:57",
		"closeGui" : "goldfisch 6/21/2015 12:57",
		"createScreenCastCaptureButton" : "goldfisch 6/22/2015 04:17",
		"createScreenCastRecordButton" : "goldfisch 6/22/2015 04:17",
		"demoMode" : "goldfisch 6/21/2015 12:57",
		"demoModeState" : "goldfisch 6/21/2015 12:57",
		"enterDemoMode" : "goldfisch 6/21/2015 12:57",
		"fontPreview" : "goldfisch 6/21/2015 12:57",
		"fontPreview:" : "goldfisch 6/21/2015 12:57",
		"inDemoMode" : "goldfisch 6/21/2015 12:57",
		"initialize" : "goldfisch 6/22/2015 03:43",
		"initializeDemoModeButton" : "goldfisch 6/22/2015 04:54",
		"initializeDemoModeButtons" : "goldfisch 6/22/2015 04:58",
		"initializeScreenCastPanel" : "goldfisch 6/22/2015 05:04",
		"initializeSlider" : "goldfisch 6/22/2015 05:39",
		"initializeStepButtonList" : "goldfisch 6/22/2015 03:30",
		"initializeToggleShowKeysButton" : "goldfisch 6/22/2015 05:02",
		"initializeWindow" : "goldfisch 6/22/2015 03:41",
		"label" : "goldfisch 6/22/2015 03:16",
		"label:" : "goldfisch 6/22/2015 03:16",
		"leaveDemoMode" : "goldfisch 6/21/2015 12:57",
		"screenCastCaptureButton" : "goldfisch 6/21/2015 12:57",
		"screenCastCaptureButton:" : "goldfisch 6/21/2015 12:57",
		"screenCastRecordButton" : "goldfisch 6/21/2015 12:57",
		"screenCastRecordButton:" : "goldfisch 6/21/2015 12:57",
		"setDemoModeState:" : "goldfisch 6/21/2015 12:57",
		"setSizeFactor:" : "goldfisch 6/21/2015 12:57",
		"showKeysStateButton" : "goldfisch 6/21/2015 12:57",
		"showKeysStateButton:" : "goldfisch 6/21/2015 12:57",
		"slider" : "goldfisch 6/21/2015 12:57",
		"slider:" : "goldfisch 6/21/2015 12:57",
		"step" : "goldfisch 6/21/2015 12:57",
		"stepButtonList" : "goldfisch 6/21/2015 12:57",
		"stepButtonList:" : "goldfisch 6/21/2015 12:57",
		"testbutton" : "goldfisch 6/22/2015 03:16",
		"testbutton:" : "goldfisch 6/22/2015 03:16",
		"toggleCaptureButton" : "goldfisch 6/21/2015 12:57",
		"toggleRecordButton" : "goldfisch 6/21/2015 12:57",
		"toggleShowKeysState" : "goldfisch 6/21/2015 12:57",
		"updateFontPreview" : "goldfisch 6/21/2015 12:57",
		"updateGui" : "goldfisch 6/22/2015 05:31",
		"window" : "goldfisch 6/21/2015 13:01",
		"window:" : "goldfisch 6/21/2015 13:01" } }
