{
	"class" : {
		"BalloonHelpFont" : "bf 5/21/2015 12:27",
		"ButtonFont" : "bf 5/21/2015 12:27",
		"CodeFont" : "bf 5/21/2015 12:27",
		"EToysFont" : "bf 5/21/2015 12:27",
		"EToysTitleFont" : "bf 5/25/2015 20:01",
		"FlapsFont" : "bf 5/21/2015 12:28",
		"HaloLabelFont" : "bf 5/25/2015 20:01",
		"ListFont" : "bf 5/21/2015 12:28",
		"MenuFont" : "bf 5/21/2015 12:28",
		"PaintBoxButtonFont" : "bf 5/21/2015 12:28",
		"SystemFont" : "bf 5/21/2015 12:28",
		"WindowTitleFont" : "bf 5/21/2015 12:28" },
	"instance" : {
		"fonts" : "bf 5/21/2015 11:53",
		"fonts:" : "bf 5/21/2015 11:53",
		"initialize" : "mj 5/27/2015 11:25",
		"initializeFontDictionary" : "mj 5/28/2015 09:14",
		"loadFonts" : "bf 5/25/2015 20:04",
		"mouseForm" : "bf 5/26/2015 10:55",
		"mouseForm:" : "bf 5/23/2015 09:31",
		"mouseHasChanged" : "bf 5/25/2015 19:10",
		"refreshFontSettings" : "mj 5/22/2015 19:16",
		"refreshWindowSize:" : "bf 6/18/2015 13:04",
		"saveFonts" : "bf 5/25/2015 20:04",
		"scaleMouseFormBy:" : "bf 5/23/2015 09:56",
		"scaleMouseFormTo:" : "bf 5/23/2015 09:57",
		"setFonts:" : "bf 6/18/2015 13:04",
		"setFontsAndWindowSize:" : "bf 6/18/2015 13:04",
		"showBigMouse" : "bf 6/29/2015 19:09",
		"showSmallMouse" : "bf 5/25/2015 19:10",
		"updateMouseToForm" : "bf 5/23/2015 09:34" } }
